Metadata-Version: 2.1
Name: litNlp
Version: 0.8.5
Summary: A fast tool for sentiment analysis model with tensorflow2.0 
Home-page: https://github.com/CarryChang/litNlp
Author: CarryChang
Author-email: coolcahng@gmail.com
License: https://www.apache.org/licenses/LICENSE-2.0
Keywords: text classification,nlp,batch predict,deep learning,tensorflow,ml
Platform: UNKNOWN
Classifier: License :: OSI Approved :: Apache Software License
Classifier: Operating System :: OS Independent
Classifier: Intended Audience :: Developers
Classifier: Intended Audience :: Education
Classifier: Intended Audience :: Science/Research
Classifier: Programming Language :: Python :: 3.5
Classifier: Programming Language :: Python :: 3.6
Classifier: Programming Language :: Python :: 3.7
Classifier: Topic :: Scientific/Engineering
Classifier: Topic :: Software Development
Classifier: Topic :: Software Development :: Libraries
Classifier: Topic :: Software Development :: Libraries :: Python Modules
Requires-Python: >=3.5
Provides-Extra: cpu
Provides-Extra: gpu
